Thermobar/Brugman_2019_Cali_Cpx.csv
Thermobar/Brugman_2019_Cali_Cpx.pkl
Thermobar/Brugman_2019_Cali_input.csv
Thermobar/Brugman_2019_Cali_input.pkl
Thermobar/Jorgenson2022_Cali_Cpx.csv
Thermobar/Jorgenson2022_Cali_Cpx.pkl
Thermobar/Jorgenson2022_Cali_input.csv
Thermobar/Jorgenson2022_Cali_input.pkl
Thermobar/ML_scaler_Petrelli2020_Cpx_Only.pkl
Thermobar/Masotta2019_Cali_Amp.csv
Thermobar/Masotta2019_Cali_input.csv
Thermobar/Masotta2019_Cali_input.pkl
Thermobar/Masotta_2013_Cali_Cpx.csv
Thermobar/Masotta_2013_Cali_Cpx.pkl
Thermobar/Masotta_2013_Cali_input.csv
Thermobar/Masotta_2013_Cali_input.pkl
Thermobar/Mutch_Cali_Amp.csv
Thermobar/Mutch_Cali_Amp.pkl
Thermobar/Mutch_Cali_input.csv
Thermobar/Mutch_Cali_input.pkl
Thermobar/NeavePutirka_2017_Cali_Cpx.csv
Thermobar/NeavePutirka_2017_Cali_Cpx.pkl
Thermobar/NeavePutirka_2017_Cali_input.csv
Thermobar/NeavePutirka_2017_Cali_input.pkl
Thermobar/Nimis_1999.py
Thermobar/Petrelli20_Cali_Cpx.csv
Thermobar/Petrelli20_Cali_Cpx.pkl
Thermobar/Petrelli20_Cali_input.csv
Thermobar/Petrelli20_Cali_input.pkl
Thermobar/Putirka16_Cali_Amp.csv
Thermobar/Putirka16_Cali_Amp.pkl
Thermobar/Putirka16_Cali_input.csv
Thermobar/Putirka16_Cali_input.pkl
Thermobar/Putirka2008_Cali_Cpx.csv
Thermobar/Putirka2008_Cali_Cpx.pkl
Thermobar/Putirka2008_Cali_input.csv
Thermobar/Putirka2008_Cali_input.pkl
Thermobar/Ridolfi_Cali_Amp.csv
Thermobar/Ridolfi_Cali_Amp.pkl
Thermobar/Ridolfi_Cali_input.csv
Thermobar/Ridolfi_Cali_input.pkl
Thermobar/Shea2022_Cali_input.csv
Thermobar/Shea2022_Cali_input.pkl
Thermobar/Wang21_Cali_Cpx.csv
Thermobar/Wang21_Cali_Cpx.pkl
Thermobar/Wang21_Cali_input.csv
Thermobar/Wang21_Cali_input.pkl
Thermobar/Waters_Lange2015_Cali_Amp.csv
Thermobar/Waters_Lange2015_Cali_input.csv
Thermobar/Waters_Lange2015_Cali_input.pkl
Thermobar/Zhang17_Cali_Amp.csv
Thermobar/Zhang17_Cali_Amp.pkl
Thermobar/Zhang17_Cali_input.csv
Thermobar/Zhang17_Cali_input.pkl
Thermobar/__init__.py
Thermobar/_version.py
Thermobar/amphibole.py
Thermobar/aztecloading.py
thermobar-1.0.67.dist-info/licenses/LICENSE.txt
thermobar-1.0.67.dist-info/METADATA
thermobar-1.0.67.dist-info/WHEEL
thermobar-1.0.67.dist-info/top_level.txt
thermobar-1.0.67.dist-info/RECORD
