Metadata-Version: 2.4
Name: thermobar
Version: 1.0.67
Summary: Thermobar
Home-page: https://github.com/PennyWieser/Thermobar
Author: Penny Wieser et al. 
Author-email: penny.wieser@gmail.com
License: MIT (with GUI use clause, see LICENSE file)
Classifier: Programming Language :: Python :: 3
Classifier: Operating System :: OS Independent
Requires-Python: >=3.9
License-File: LICENSE.txt
Requires-Dist: pandas
Requires-Dist: numpy
Requires-Dist: python-ternary
Requires-Dist: matplotlib
Requires-Dist: scikit-learn>=1.3
Requires-Dist: scipy
Requires-Dist: tqdm
Requires-Dist: statsmodels
Requires-Dist: openpyxl
Requires-Dist: pathlib
Dynamic: author
Dynamic: author-email
Dynamic: classifier
Dynamic: description
Dynamic: description-content-type
Dynamic: home-page
Dynamic: license
Dynamic: license-file
Dynamic: requires-dist
Dynamic: requires-python
Dynamic: summary
